README.txt
setup.py
imagetools/__init__.py
imagetools/batchTools.py
imagetools.egg-info/PKG-INFO
imagetools.egg-info/SOURCES.txt
imagetools.egg-info/dependency_links.txt
imagetools.egg-info/top_level.txt
imagetools.egg-info/zip-safe