Metadata-Version: 1.1
Name: imagetools
Version: 1.0.0
Summary: This is a tool for image batch processing.
Home-page: https://zhaoxuhui.top
Author: zhaoxuhui
Author-email: zhaoxuhui@whu.edu.cn
License: MIT
Keywords: test python package
Platform: UNKNOWN
Classifier: License :: OSI Approved :: MIT License
Classifier: Programming Language :: Python
Classifier: Intended Audience :: Developers
Classifier: Operating System :: OS Independent
